DorisClient/AdminSession.py
DorisClient/BaseSession.py
DorisClient/MetaSession.py
DorisClient/_BaseSql.py
DorisClient/__init__.py
DorisClient-1.2.22.dist-info/LICENSE
DorisClient-1.2.22.dist-info/METADATA
DorisClient-1.2.22.dist-info/WHEEL
DorisClient-1.2.22.dist-info/top_level.txt
DorisClient-1.2.22.dist-info/RECORD
