Metadata-Version: 2.1
Name: DorisClient
Version: 1.2.22
Summary: python for apache-doris
Home-page: https://github.com/TurboWay/DorisClient
Author: Way
Author-email: 1143496751@qq.com
License: Apache License 2.0
Platform: any
License-File: LICENSE
Requires-Dist: requests
Requires-Dist: PyMySQL
